ConfigHelper/__init__.py
tests/__init__.py
PyAmdecoder-0.0.3.dist-info/LICENSE
PyAmdecoder-0.0.3.dist-info/METADATA
PyAmdecoder-0.0.3.dist-info/WHEEL
PyAmdecoder-0.0.3.dist-info/top_level.txt
PyAmdecoder-0.0.3.dist-info/RECORD
